autotrash/__init__.py
autotrash/app.py
autotrash/options.py
autotrash-0.4.7.dist-info/LICENSE.txt
autotrash-0.4.7.dist-info/METADATA
autotrash-0.4.7.dist-info/WHEEL
autotrash-0.4.7.dist-info/entry_points.txt
autotrash-0.4.7.dist-info/RECORD
