Metadata-Version: 2.1
Name: autotrash
Version: 0.4.7
Summary: Script to automatically purge old trash
Home-page: https://github.com/bneijt/autotrash
Author: Bram Neijt
Author-email: bram@neijt.nl
Requires-Python: >=3.8,<4
Classifier: Environment :: Console
Classifier: License :: OSI Approved :: GNU General Public License v3 (GPLv3)
Classifier: Programming Language :: Python :: 3
Classifier: Programming Language :: Python :: 3.8
Classifier: Programming Language :: Python :: 3.9
Classifier: Programming Language :: Python :: 3.10
Classifier: Programming Language :: Python :: 3.11
Project-URL: Repository, https://github.com/bneijt/autotrash
